MANIFEST.in
README
setup.cfg
setup.py
pydart/__init__.py
pydart/body.py
pydart/c3d.py
pydart/contact.py
pydart/dof.py
pydart/marker.py
pydart/misc.py
pydart/numpy.i
pydart/pydart.py
pydart/pydart_api.cpp
pydart/pydart_api.h
pydart/pydart_api.i
pydart/pydart_api.py
pydart/skel_vector.py
pydart/skeleton.py
pydart.egg-info/PKG-INFO
pydart.egg-info/SOURCES.txt
pydart.egg-info/dependency_links.txt
pydart.egg-info/requires.txt
pydart.egg-info/top_level.txt