Metadata-Version: 1.0
Name: pydart
Version: 0.1.14
Summary: Python Interface for DART Simulator
Home-page: https://github.com/sehoonha/pydart
Author: Sehoon Ha
Author-email: sehoon.ha@gmail.com
License: BSD
Platform: UNKNOWN
